{
    "data": {
        "user": {
            "edge_followed_by": {
                "count": 597,
                "edges": [
                    {
                        "node": {
                            "followed_by_viewer": false,
                            "full_name": "\u0414\u0435\u0440\u0435\u0432\u044f\u043d\u043d\u0430\u044f \u043f\u043e\u0441\u0443\u0434\u043a\u0430 \u0438 \u0438\u0433\u0440\u0443\u0448\u043a\u0438",
                            "id": "21494473014",
                            "is_private": false,
                            "is_verified": false,
                            "profile_pic_url": "https://scontent-frt3-2.cdninstagram.com/v/t51.2885-19/s150x150/100948930_532365194096706_3612023459636314112_n.jpg?_nc_ht=scontent-frt3-2.cdninstagram.com&_nc_ohc=XdgKAAO-GAgAX-zZzfW&oh=4bafcea02ca438c1b3380ae64d5640b2&oe=5FD13357",
                            "reel": {
                                "expiring_at": 1604915178,
                                "has_pride_media": false,
                                "id": "21494473014",
                                "latest_reel_media": 0,
                                "owner": {
                                    "__typename": "GraphUser",
                                    "id": "21494473014",
                                    "profile_pic_url": "https://scontent-frt3-2.cdninstagram.com/v/t51.2885-19/s150x150/100948930_532365194096706_3612023459636314112_n.jpg?_nc_ht=scontent-frt3-2.cdninstagram.com&_nc_ohc=XdgKAAO-GAgAX-zZzfW&oh=4bafcea02ca438c1b3380ae64d5640b2&oe=5FD13357",
                                    "username": "woodegorka"
                                },
                                "seen": null
                            },
                            "requested_by_viewer": false,
                            "username": "woodegorka"
                        }
                    },
                    {
                        "node": {
                            "followed_by_viewer": false,
                            "full_name": "\u041b\u0435\u043d\u0430 \u0412\u043e\u0439\u0442\u0435\u0445",
                            "id": "18792939039",
                            "is_private": false,
                            "is_verified": false,
                            "profile_pic_url": "https://scontent-frt3-2.cdninstagram.com/v/t51.2885-19/s150x150/67438122_431842837539235_2140409896993030144_n.jpg?_nc_ht=scontent-frt3-2.cdninstagram.com&_nc_ohc=Wx6jP-Z1KBsAX8D_9i8&oh=b3d2267f58f4fd95bb5159939698c400&oe=5FD0AE21",
                            "reel": {
                                "expiring_at": 1604915178,
                                "has_pride_media": false,
                                "id": "18792939039",
                                "latest_reel_media": 0,
                                "owner": {
                                    "__typename": "GraphUser",
                                    "id": "18792939039",
                                    "profile_pic_url": "https://scontent-frt3-2.cdninstagram.com/v/t51.2885-19/s150x150/67438122_431842837539235_2140409896993030144_n.jpg?_nc_ht=scontent-frt3-2.cdninstagram.com&_nc_ohc=Wx6jP-Z1KBsAX8D_9i8&oh=b3d2267f58f4fd95bb5159939698c400&oe=5FD0AE21",
                                    "username": "lenavth_"
                                },
                                "seen": null
                            },
                            "requested_by_viewer": false,
                            "username": "lenavth_"
                        }
                    },
                    {
                        "node": {
                            "followed_by_viewer": false,
                            "full_name": "",
                            "id": "6887916037",
                            "is_private": true,
                            "is_verified": false,
                            "profile_pic_url": "https://scontent-frt3-2.cdninstagram.com/v/t51.2885-19/s150x150/39665466_511234689288437_9213138860660228096_n.jpg?_nc_ht=scontent-frt3-2.cdninstagram.com&_nc_ohc=bnHD68SEaf4AX9aFL7x&oh=7d957dc1bcf82e8737557a63a112a011&oe=5FD24CC4",
                            "reel": {
                                "expiring_at": 1604915178,
                                "has_pride_media": false,
                                "id": "6887916037",
                                "latest_reel_media": null,
                                "owner": {
                                    "__typename": "GraphUser",
                                    "id": "6887916037",
                                    "profile_pic_url": "https://scontent-frt3-2.cdninstagram.com/v/t51.2885-19/s150x150/39665466_511234689288437_9213138860660228096_n.jpg?_nc_ht=scontent-frt3-2.cdninstagram.com&_nc_ohc=bnHD68SEaf4AX9aFL7x&oh=7d957dc1bcf82e8737557a63a112a011&oe=5FD24CC4",
                                    "username": "kudriavishna"
                                },
                                "seen": null
                            },
                            "requested_by_viewer": false,
                            "username": "kudriavishna"
                        }
                    },
                    {
                        "node": {
                            "followed_by_viewer": false,
                            "full_name": "\u0418\u0440\u0438\u043d\u0430 \u0411\u0435\u043b\u043a\u0438\u043d\u0430",
                            "id": "240721947",
                            "is_private": false,
                            "is_verified": false,
                            "profile_pic_url": "https://scontent-frt3-2.cdninstagram.com/v/t51.2885-19/s150x150/101953507_550975175856753_6283173180042527660_n.jpg?_nc_ht=scontent-frt3-2.cdninstagram.com&_nc_ohc=rQOxxjitqCUAX83AdAI&oh=e9e8b3555514e4a15b870ba356ba67e6&oe=5FD1865E",
                            "reel": {
                                "expiring_at": 1604915178,
                                "has_pride_media": false,
                                "id": "240721947",
                                "latest_reel_media": 0,
                                "owner": {
                                    "__typename": "GraphUser",
                                    "id": "240721947",
                                    "profile_pic_url": "https://scontent-frt3-2.cdninstagram.com/v/t51.2885-19/s150x150/101953507_550975175856753_6283173180042527660_n.jpg?_nc_ht=scontent-frt3-2.cdninstagram.com&_nc_ohc=rQOxxjitqCUAX83AdAI&oh=e9e8b3555514e4a15b870ba356ba67e6&oe=5FD1865E",
                                    "username": "belkina.irina.a"
                                },
                                "seen": null
                            },
                            "requested_by_viewer": false,
                            "username": "belkina.irina.a"
                        }
                    },
                    {
                        "node": {
                            "followed_by_viewer": false,
                            "full_name": "\u0414\u0435\u0442\u0441\u043a\u0438\u0438\u0306 \u0434\u0435\u043a\u043e\u0440\u2022\u0418\u0433\u0440\u0443\u0448\u043a\u0438\u2022\u041f\u043e\u0434\u0430\u0440\u043a\u0438",
                            "id": "26052191366",
                            "is_private": false,
                            "is_verified": false,
                            "profile_pic_url": "https://scontent-frt3-2.cdninstagram.com/v/t51.2885-19/s150x150/75300805_2162622474044941_4362896000537329664_n.jpg?_nc_ht=scontent-frt3-2.cdninstagram.com&_nc_ohc=2rq71ktvlsEAX9ua_7u&oh=a9794e9301b5c3b8ce897176268f9997&oe=5FCF528B",
                            "reel": {
                                "expiring_at": 1604915178,
                                "has_pride_media": false,
                                "id": "26052191366",
                                "latest_reel_media": 0,
                                "owner": {
                                    "__typename": "GraphUser",
                                    "id": "26052191366",
                                    "profile_pic_url": "https://scontent-frt3-2.cdninstagram.com/v/t51.2885-19/s150x150/75300805_2162622474044941_4362896000537329664_n.jpg?_nc_ht=scontent-frt3-2.cdninstagram.com&_nc_ohc=2rq71ktvlsEAX9ua_7u&oh=a9794e9301b5c3b8ce897176268f9997&oe=5FCF528B",
                                    "username": "_myboni_"
                                },
                                "seen": null
                            },
                            "requested_by_viewer": false,
                            "username": "_myboni_"
                        }
                    },
                    {
                        "node": {
                            "followed_by_viewer": false,
                            "full_name": "\u0411\u041e\u0420\u0422\u0418\u041a\u0418 \u2022\u041a\u041e\u041a\u041e\u041d\u042b \u2022\u0422\u0415\u041a\u0421\u0422\u0418\u041b\u042c",
                            "id": "15047501633",
                            "is_private": false,
                            "is_verified": false,
                            "profile_pic_url": "https://scontent-frt3-2.cdninstagram.com/v/t51.2885-19/s150x150/121235199_201721144667064_495555343552705765_n.jpg?_nc_ht=scontent-frt3-2.cdninstagram.com&_nc_ohc=J3JWQY8OMA0AX8ow9tM&oh=4c14c359eea129063cfa96fba0aa41fa&oe=5FD1310A",
                            "reel": {
                                "expiring_at": 1604915178,
                                "has_pride_media": false,
                                "id": "15047501633",
                                "latest_reel_media": 0,
                                "owner": {
                                    "__typename": "GraphUser",
                                    "id": "15047501633",
                                    "profile_pic_url": "https://scontent-frt3-2.cdninstagram.com/v/t51.2885-19/s150x150/121235199_201721144667064_495555343552705765_n.jpg?_nc_ht=scontent-frt3-2.cdninstagram.com&_nc_ohc=J3JWQY8OMA0AX8ow9tM&oh=4c14c359eea129063cfa96fba0aa41fa&oe=5FD1310A",
                                    "username": "lilipups_nn"
                                },
                                "seen": null
                            },
                            "requested_by_viewer": false,
                            "username": "lilipups_nn"
                        }
                    },
                    {
                        "node": {
                            "followed_by_viewer": false,
                            "full_name": "alfiya",
                            "id": "180201475",
                            "is_private": true,
                            "is_verified": false,
                            "profile_pic_url": "https://scontent-frt3-2.cdninstagram.com/v/t51.2885-19/s150x150/52043279_394401821109426_4343763841084030976_n.jpg?_nc_ht=scontent-frt3-2.cdninstagram.com&_nc_ohc=HjImFYUNiIgAX9tSclu&oh=a0ab5ff995d10b102a0d39a70a9d9257&oe=5FD130BC",
                            "reel": {
                                "expiring_at": 1604915178,
                                "has_pride_media": false,
                                "id": "180201475",
                                "latest_reel_media": null,
                                "owner": {
                                    "__typename": "GraphUser",
                                    "id": "180201475",
                                    "profile_pic_url": "https://scontent-frt3-2.cdninstagram.com/v/t51.2885-19/s150x150/52043279_394401821109426_4343763841084030976_n.jpg?_nc_ht=scontent-frt3-2.cdninstagram.com&_nc_ohc=HjImFYUNiIgAX9tSclu&oh=a0ab5ff995d10b102a0d39a70a9d9257&oe=5FD130BC",
                                    "username": "alfiyaya"
                                },
                                "seen": null
                            },
                            "requested_by_viewer": false,
                            "username": "alfiyaya"
                        }
                    },
                    {
                        "node": {
                            "followed_by_viewer": false,
                            "full_name": "",
                            "id": "1153308514",
                            "is_private": true,
                            "is_verified": false,
                            "profile_pic_url": "https://scontent-frt3-2.cdninstagram.com/v/t51.2885-19/s150x150/123705909_853508298733123_1357567340865498625_n.jpg?_nc_ht=scontent-frt3-2.cdninstagram.com&_nc_ohc=D1YMJE6TbQ4AX_O1sfk&oh=90f01c2480aed96cb535c0540678bc37&oe=5FD01ED5",
                            "reel": {
                                "expiring_at": 1604915178,
                                "has_pride_media": false,
                                "id": "1153308514",
                                "latest_reel_media": null,
                                "owner": {
                                    "__typename": "GraphUser",
                                    "id": "1153308514",
                                    "profile_pic_url": "https://scontent-frt3-2.cdninstagram.com/v/t51.2885-19/s150x150/123705909_853508298733123_1357567340865498625_n.jpg?_nc_ht=scontent-frt3-2.cdninstagram.com&_nc_ohc=D1YMJE6TbQ4AX_O1sfk&oh=90f01c2480aed96cb535c0540678bc37&oe=5FD01ED5",
                                    "username": "ksen_net"
                                },
                                "seen": null
                            },
                            "requested_by_viewer": false,
                            "username": "ksen_net"
                        }
                    },
                    {
                        "node": {
                            "followed_by_viewer": false,
                            "full_name": "\u0410\u043d\u0430\u0441\u0442\u0430\u0441\u0438\u044f \u0421\u043e\u0440\u043e\u043a\u0438\u043d\u0430",
                            "id": "27761087798",
                            "is_private": false,
                            "is_verified": false,
                            "profile_pic_url": "https://scontent-frt3-2.cdninstagram.com/v/t51.2885-19/s150x150/82788958_558296834757086_6057972798876286976_n.jpg?_nc_ht=scontent-frt3-2.cdninstagram.com&_nc_ohc=x_FnWZ1xZKcAX99SUct&oh=e953e5ff75348eefb6d5e86ea1da9d28&oe=5FCF519C",
                            "reel": {
                                "expiring_at": 1604915178,
                                "has_pride_media": false,
                                "id": "27761087798",
                                "latest_reel_media": 1604813968,
                                "owner": {
                                    "__typename": "GraphUser",
                                    "id": "27761087798",
                                    "profile_pic_url": "https://scontent-frt3-2.cdninstagram.com/v/t51.2885-19/s150x150/82788958_558296834757086_6057972798876286976_n.jpg?_nc_ht=scontent-frt3-2.cdninstagram.com&_nc_ohc=x_FnWZ1xZKcAX99SUct&oh=e953e5ff75348eefb6d5e86ea1da9d28&oe=5FCF519C",
                                    "username": "asorokina__"
                                },
                                "seen": null
                            },
                            "requested_by_viewer": false,
                            "username": "asorokina__"
                        }
                    },
                    {
                        "node": {
                            "followed_by_viewer": false,
                            "full_name": "\ud83d\udc0b\ud83d\udc9c",
                            "id": "271415524",
                            "is_private": false,
                            "is_verified": false,
                            "profile_pic_url": "https://scontent-frt3-2.cdninstagram.com/v/t51.2885-19/1597757_1516048888609601_1096528907_a.jpg?_nc_ht=scontent-frt3-2.cdninstagram.com&_nc_ohc=ZSKFyHUp6akAX-MNsxY&oh=0a53d92856c09f651448c7030012e6e4&oe=5FD33314",
                            "reel": {
                                "expiring_at": 1604915178,
                                "has_pride_media": false,
                                "id": "271415524",
                                "latest_reel_media": 1604776711,
                                "owner": {
                                    "__typename": "GraphUser",
                                    "id": "271415524",
                                    "profile_pic_url": "https://scontent-frt3-2.cdninstagram.com/v/t51.2885-19/1597757_1516048888609601_1096528907_a.jpg?_nc_ht=scontent-frt3-2.cdninstagram.com&_nc_ohc=ZSKFyHUp6akAX-MNsxY&oh=0a53d92856c09f651448c7030012e6e4&oe=5FD33314",
                                    "username": "_kristina.popleskina_"
                                },
                                "seen": null
                            },
                            "requested_by_viewer": false,
                            "username": "_kristina.popleskina_"
                        }
                    },
                    {
                        "node": {
                            "followed_by_viewer": false,
                            "full_name": "\u0410\u043d\u044f \u042d\u043a\u043b\u0435\u043a\u0442\u0438\u043a\u0430",
                            "id": "7919818772",
                            "is_private": false,
                            "is_verified": false,
                            "profile_pic_url": "https://scontent-frt3-2.cdninstagram.com/v/t51.2885-19/s150x150/106565346_2990951684366276_1829196284941841876_n.jpg?_nc_ht=scontent-frt3-2.cdninstagram.com&_nc_ohc=Bfi3x1-aAosAX8NYY4L&oh=85ff58edf88539986056ef6649bcbf4c&oe=5FD053B5",
                            "reel": {
                                "expiring_at": 1604915178,
                                "has_pride_media": false,
                                "id": "7919818772",
                                "latest_reel_media": 0,
                                "owner": {
                                    "__typename": "GraphUser",
                                    "id": "7919818772",
                                    "profile_pic_url": "https://scontent-frt3-2.cdninstagram.com/v/t51.2885-19/s150x150/106565346_2990951684366276_1829196284941841876_n.jpg?_nc_ht=scontent-frt3-2.cdninstagram.com&_nc_ohc=Bfi3x1-aAosAX8NYY4L&oh=85ff58edf88539986056ef6649bcbf4c&oe=5FD053B5",
                                    "username": "aneklektika"
                                },
                                "seen": null
                            },
                            "requested_by_viewer": false,
                            "username": "aneklektika"
                        }
                    },
                    {
                        "node": {
                            "followed_by_viewer": false,
                            "full_name": "Anton  Shabanov",
                            "id": "250209173",
                            "is_private": true,
                            "is_verified": false,
                            "profile_pic_url": "https://scontent-frt3-2.cdninstagram.com/v/t51.2885-19/s150x150/21909932_449209448809800_1832717443475177472_n.jpg?_nc_ht=scontent-frt3-2.cdninstagram.com&_nc_ohc=1hGgw8FB3moAX9fHCYU&oh=3468fecc7e9267f9110c4dfeccea71d3&oe=5FD077DB",
                            "reel": {
                                "expiring_at": 1604915178,
                                "has_pride_media": false,
                                "id": "250209173",
                                "latest_reel_media": null,
                                "owner": {
                                    "__typename": "GraphUser",
                                    "id": "250209173",
                                    "profile_pic_url": "https://scontent-frt3-2.cdninstagram.com/v/t51.2885-19/s150x150/21909932_449209448809800_1832717443475177472_n.jpg?_nc_ht=scontent-frt3-2.cdninstagram.com&_nc_ohc=1hGgw8FB3moAX9fHCYU&oh=3468fecc7e9267f9110c4dfeccea71d3&oe=5FD077DB",
                                    "username": "shabanovant"
                                },
                                "seen": null
                            },
                            "requested_by_viewer": false,
                            "username": "shabanovant"
                        }
                    },
                    {
                        "node": {
                            "followed_by_viewer": false,
                            "full_name": "",
                            "id": "25579155020",
                            "is_private": true,
                            "is_verified": false,
                            "profile_pic_url": "https://scontent-frt3-2.cdninstagram.com/v/t51.2885-19/s150x150/90973143_2277828719188462_8448716350775361536_n.jpg?_nc_ht=scontent-frt3-2.cdninstagram.com&_nc_ohc=MZxoWLpyErYAX-MoJi9&oh=b9eaaff0d9ea8bba0632bd998cf47dd9&oe=5FD1A976",
                            "reel": {
                                "expiring_at": 1604915178,
                                "has_pride_media": false,
                                "id": "25579155020",
                                "latest_reel_media": null,
                                "owner": {
                                    "__typename": "GraphUser",
                                    "id": "25579155020",
                                    "profile_pic_url": "https://scontent-frt3-2.cdninstagram.com/v/t51.2885-19/s150x150/90973143_2277828719188462_8448716350775361536_n.jpg?_nc_ht=scontent-frt3-2.cdninstagram.com&_nc_ohc=MZxoWLpyErYAX-MoJi9&oh=b9eaaff0d9ea8bba0632bd998cf47dd9&oe=5FD1A976",
                                    "username": "brisck_vi"
                                },
                                "seen": null
                            },
                            "requested_by_viewer": false,
                            "username": "brisck_vi"
                        }
                    },
                    {
                        "node": {
                            "followed_by_viewer": false,
                            "full_name": "Maria Orlova",
                            "id": "34888574556",
                            "is_private": true,
                            "is_verified": false,
                            "profile_pic_url": "https://scontent-den4-1.cdninstagram.com/v/t51.2885-19/44884218_345707102882519_2446069589734326272_n.jpg?_nc_ht=scontent-den4-1.cdninstagram.com&_nc_ohc=mNn0cxNHoc8AX8LB9MW&oh=ed9a0d78a4622c44fe07e2761fdcff76&oe=5FD1848F&ig_cache_key=YW5vbnltb3VzX3Byb2ZpbGVfcGlj.2",
                            "reel": {
                                "expiring_at": 1604915178,
                                "has_pride_media": false,
                                "id": "34888574556",
                                "latest_reel_media": null,
                                "owner": {
                                    "__typename": "GraphUser",
                                    "id": "34888574556",
                                    "profile_pic_url": "https://scontent-den4-1.cdninstagram.com/v/t51.2885-19/44884218_345707102882519_2446069589734326272_n.jpg?_nc_ht=scontent-den4-1.cdninstagram.com&_nc_ohc=mNn0cxNHoc8AX8LB9MW&oh=ed9a0d78a4622c44fe07e2761fdcff76&oe=5FD1848F&ig_cache_key=YW5vbnltb3VzX3Byb2ZpbGVfcGlj.2",
                                    "username": "_maria.alada"
                                },
                                "seen": null
                            },
                            "requested_by_viewer": false,
                            "username": "_maria.alada"
                        }
                    },
                    {
                        "node": {
                            "followed_by_viewer": false,
                            "full_name": "\u041a\u043e\u0432\u0430\u043b\u0435\u0432\u0441\u043a\u0430\u044f \u041d\u0430\u0442\u0430\u0448\u0430",
                            "id": "7118290571",
                            "is_private": false,
                            "is_verified": false,
                            "profile_pic_url": "https://scontent-frt3-2.cdninstagram.com/v/t51.2885-19/s150x150/56386611_2171269242963450_4706149198423130112_n.jpg?_nc_ht=scontent-frt3-2.cdninstagram.com&_nc_ohc=FYQVdLxf2QAAX9sVX8Y&oh=a1535db490386c4ed7a22283873877d8&oe=5FD2382B",
                            "reel": {
                                "expiring_at": 1604915178,
                                "has_pride_media": false,
                                "id": "7118290571",
                                "latest_reel_media": 0,
                                "owner": {
                                    "__typename": "GraphUser",
                                    "id": "7118290571",
                                    "profile_pic_url": "https://scontent-frt3-2.cdninstagram.com/v/t51.2885-19/s150x150/56386611_2171269242963450_4706149198423130112_n.jpg?_nc_ht=scontent-frt3-2.cdninstagram.com&_nc_ohc=FYQVdLxf2QAAX9sVX8Y&oh=a1535db490386c4ed7a22283873877d8&oe=5FD2382B",
                                    "username": "kovalevskay_natasha"
                                },
                                "seen": null
                            },
                            "requested_by_viewer": false,
                            "username": "kovalevskay_natasha"
                        }
                    },
                    {
                        "node": {
                            "followed_by_viewer": false,
                            "full_name": "LIH CLOTHES\u2022\u0412\u041e\u041b\u0428\u0415\u0411\u0421\u0422\u0412\u041e \u0412\u041d\u0423\u0422\u0420\u0418\ud83d\udcab",
                            "id": "2306333060",
                            "is_private": false,
                            "is_verified": false,
                            "profile_pic_url": "https://scontent-frt3-2.cdninstagram.com/v/t51.2885-19/s150x150/69282570_748119485669021_4473341582770176_n.jpg?_nc_ht=scontent-frt3-2.cdninstagram.com&_nc_ohc=yvV-s1A1AAsAX_kIsN0&oh=79a09c92e689562cf04b7f795b4dcd57&oe=5FCF7328",
                            "reel": {
                                "expiring_at": 1604915178,
                                "has_pride_media": false,
                                "id": "2306333060",
                                "latest_reel_media": 1604824171,
                                "owner": {
                                    "__typename": "GraphUser",
                                    "id": "2306333060",
                                    "profile_pic_url": "https://scontent-frt3-2.cdninstagram.com/v/t51.2885-19/s150x150/69282570_748119485669021_4473341582770176_n.jpg?_nc_ht=scontent-frt3-2.cdninstagram.com&_nc_ohc=yvV-s1A1AAsAX_kIsN0&oh=79a09c92e689562cf04b7f795b4dcd57&oe=5FCF7328",
                                    "username": "l_i_h_clothes"
                                },
                                "seen": null
                            },
                            "requested_by_viewer": false,
                            "username": "l_i_h_clothes"
                        }
                    },
                    {
                        "node": {
                            "followed_by_viewer": false,
                            "full_name": "\u041f\u043e\u043b\u044f\u043a\u043e\u0432\u0430 \u0418\u043b\u043e\u043d\u0430",
                            "id": "3269016560",
                            "is_private": true,
                            "is_verified": false,
                            "profile_pic_url": "https://scontent-frt3-2.cdninstagram.com/v/t51.2885-19/s150x150/36544441_174876136593461_6952172135066370048_n.jpg?_nc_ht=scontent-frt3-2.cdninstagram.com&_nc_ohc=LqWDbyCpvsYAX9V0R-W&oh=da5fac7767eed5f2fb7548b5bce7da07&oe=5FD15FFC",
                            "reel": {
                                "expiring_at": 1604915178,
                                "has_pride_media": false,
                                "id": "3269016560",
                                "latest_reel_media": null,
                                "owner": {
                                    "__typename": "GraphUser",
                                    "id": "3269016560",
                                    "profile_pic_url": "https://scontent-frt3-2.cdninstagram.com/v/t51.2885-19/s150x150/36544441_174876136593461_6952172135066370048_n.jpg?_nc_ht=scontent-frt3-2.cdninstagram.com&_nc_ohc=LqWDbyCpvsYAX9V0R-W&oh=da5fac7767eed5f2fb7548b5bce7da07&oe=5FD15FFC",
                                    "username": "dr.polyakova.ilona"
                                },
                                "seen": null
                            },
                            "requested_by_viewer": false,
                            "username": "dr.polyakova.ilona"
                        }
                    },
                    {
                        "node": {
                            "followed_by_viewer": false,
                            "full_name": "\u042e\u043b\u0438\u044f \u0428\u043c\u0430\u0442\u043a\u043e\u0432\u0430",
                            "id": "21719521902",
                            "is_private": false,
                            "is_verified": false,
                            "profile_pic_url": "https://scontent-frt3-2.cdninstagram.com/v/t51.2885-19/s150x150/123174318_143338290829404_8190636408483270663_n.jpg?_nc_ht=scontent-frt3-2.cdninstagram.com&_nc_ohc=R_aw6F7HKrUAX9CPLP_&oh=9df93f68eb68dd44345564db76efccc8&oe=5FCFE730",
                            "reel": {
                                "expiring_at": 1604915178,
                                "has_pride_media": false,
                                "id": "21719521902",
                                "latest_reel_media": 0,
                                "owner": {
                                    "__typename": "GraphUser",
                                    "id": "21719521902",
                                    "profile_pic_url": "https://scontent-frt3-2.cdninstagram.com/v/t51.2885-19/s150x150/123174318_143338290829404_8190636408483270663_n.jpg?_nc_ht=scontent-frt3-2.cdninstagram.com&_nc_ohc=R_aw6F7HKrUAX9CPLP_&oh=9df93f68eb68dd44345564db76efccc8&oe=5FCFE730",
                                    "username": "shmatkovaiul"
                                },
                                "seen": null
                            },
                            "requested_by_viewer": false,
                            "username": "shmatkovaiul"
                        }
                    },
                    {
                        "node": {
                            "followed_by_viewer": false,
                            "full_name": "Olga Ulyanova",
                            "id": "1706512261",
                            "is_private": false,
                            "is_verified": false,
                            "profile_pic_url": "https://scontent-frt3-2.cdninstagram.com/v/t51.2885-19/s150x150/74405880_485674628740587_1868736190270668800_n.jpg?_nc_ht=scontent-frt3-2.cdninstagram.com&_nc_ohc=9S5z74kqrTwAX8IdgMq&oh=02de424762caf9266b45f8b4863035e6&oe=5FD19353",
                            "reel": {
                                "expiring_at": 1604915178,
                                "has_pride_media": false,
                                "id": "1706512261",
                                "latest_reel_media": 0,
                                "owner": {
                                    "__typename": "GraphUser",
                                    "id": "1706512261",
                                    "profile_pic_url": "https://scontent-frt3-2.cdninstagram.com/v/t51.2885-19/s150x150/74405880_485674628740587_1868736190270668800_n.jpg?_nc_ht=scontent-frt3-2.cdninstagram.com&_nc_ohc=9S5z74kqrTwAX8IdgMq&oh=02de424762caf9266b45f8b4863035e6&oe=5FD19353",
                                    "username": "olyapics"
                                },
                                "seen": null
                            },
                            "requested_by_viewer": false,
                            "username": "olyapics"
                        }
                    },
                    {
                        "node": {
                            "followed_by_viewer": false,
                            "full_name": "\u041c\u0430\u0440\u0438\u044f \u041c\u0430\u0440\u0438\u044f",
                            "id": "7949927036",
                            "is_private": false,
                            "is_verified": false,
                            "profile_pic_url": "https://scontent-frt3-2.cdninstagram.com/v/t51.2885-19/s150x150/123317027_3877762555567266_2389284537046915532_n.jpg?_nc_ht=scontent-frt3-2.cdninstagram.com&_nc_ohc=mybQgtC4WdsAX_Ysywq&oh=2499fc18f956bf0f73d64170c8dff203&oe=5FCFD546",
                            "reel": {
                                "expiring_at": 1604915178,
                                "has_pride_media": false,
                                "id": "7949927036",
                                "latest_reel_media": 1604820376,
                                "owner": {
                                    "__typename": "GraphUser",
                                    "id": "7949927036",
                                    "profile_pic_url": "https://scontent-frt3-2.cdninstagram.com/v/t51.2885-19/s150x150/123317027_3877762555567266_2389284537046915532_n.jpg?_nc_ht=scontent-frt3-2.cdninstagram.com&_nc_ohc=mybQgtC4WdsAX_Ysywq&oh=2499fc18f956bf0f73d64170c8dff203&oe=5FCFD546",
                                    "username": "mamoshka.m"
                                },
                                "seen": null
                            },
                            "requested_by_viewer": false,
                            "username": "mamoshka.m"
                        }
                    },
                    {
                        "node": {
                            "followed_by_viewer": false,
                            "full_name": "\u00b0\ud83c\udf3f\u00b0olesya kotova\u00b0\ud83c\udf3f\u00b0",
                            "id": "1694719158",
                            "is_private": true,
                            "is_verified": false,
                            "profile_pic_url": "https://scontent-frt3-2.cdninstagram.com/v/t51.2885-19/s150x150/120735164_343468323558211_1147834610756875886_n.jpg?_nc_ht=scontent-frt3-2.cdninstagram.com&_nc_ohc=5JjN46GuOzEAX_I6zjC&oh=0ee194497add5745721da2eb93be977b&oe=5FCF5FC4",
                            "reel": {
                                "expiring_at": 1604915178,
                                "has_pride_media": false,
                                "id": "1694719158",
                                "latest_reel_media": null,
                                "owner": {
                                    "__typename": "GraphUser",
                                    "id": "1694719158",
                                    "profile_pic_url": "https://scontent-frt3-2.cdninstagram.com/v/t51.2885-19/s150x150/120735164_343468323558211_1147834610756875886_n.jpg?_nc_ht=scontent-frt3-2.cdninstagram.com&_nc_ohc=5JjN46GuOzEAX_I6zjC&oh=0ee194497add5745721da2eb93be977b&oe=5FCF5FC4",
                                    "username": "_olesya_kot_"
                                },
                                "seen": null
                            },
                            "requested_by_viewer": false,
                            "username": "_olesya_kot_"
                        }
                    },
                    {
                        "node": {
                            "followed_by_viewer": false,
                            "full_name": "\ud83c\udf3f \u041c\u0430\u043c\u0430 \u042e\u043b\u044f",
                            "id": "5375206438",
                            "is_private": false,
                            "is_verified": false,
                            "profile_pic_url": "https://scontent-frt3-2.cdninstagram.com/v/t51.2885-19/s150x150/36652367_1912218712189523_404190829536608256_n.jpg?_nc_ht=scontent-frt3-2.cdninstagram.com&_nc_ohc=rBvif7OzzOEAX804IF7&oh=518267c44e35444cb57d588aba72e8f0&oe=5FD19574",
                            "reel": {
                                "expiring_at": 1604915178,
                                "has_pride_media": false,
                                "id": "5375206438",
                                "latest_reel_media": 0,
                                "owner": {
                                    "__typename": "GraphUser",
                                    "id": "5375206438",
                                    "profile_pic_url": "https://scontent-frt3-2.cdninstagram.com/v/t51.2885-19/s150x150/36652367_1912218712189523_404190829536608256_n.jpg?_nc_ht=scontent-frt3-2.cdninstagram.com&_nc_ohc=rBvif7OzzOEAX804IF7&oh=518267c44e35444cb57d588aba72e8f0&oe=5FD19574",
                                    "username": "vigzalovamur"
                                },
                                "seen": null
                            },
                            "requested_by_viewer": false,
                            "username": "vigzalovamur"
                        }
                    },
                    {
                        "node": {
                            "followed_by_viewer": false,
                            "full_name": "\u0414\u0418\u0417\u0410\u0418\u0306\u041d\u0415\u0420 \u0418\u041d\u0422\u0415\u0420\u042c\u0415\u0420\u041e\u0412",
                            "id": "6627785412",
                            "is_private": false,
                            "is_verified": false,
                            "profile_pic_url": "https://scontent-frt3-2.cdninstagram.com/v/t51.2885-19/s150x150/81471923_713218152848409_4928520267006727100_n.jpg?_nc_ht=scontent-frt3-2.cdninstagram.com&_nc_ohc=UfQ9ldhLqAMAX_dBp-N&oh=4fd8fa91ebe3f7b6826bc198b38dd67f&oe=5FD1F073",
                            "reel": {
                                "expiring_at": 1604915178,
                                "has_pride_media": false,
                                "id": "6627785412",
                                "latest_reel_media": 0,
                                "owner": {
                                    "__typename": "GraphUser",
                                    "id": "6627785412",
                                    "profile_pic_url": "https://scontent-frt3-2.cdninstagram.com/v/t51.2885-19/s150x150/81471923_713218152848409_4928520267006727100_n.jpg?_nc_ht=scontent-frt3-2.cdninstagram.com&_nc_ohc=UfQ9ldhLqAMAX_dBp-N&oh=4fd8fa91ebe3f7b6826bc198b38dd67f&oe=5FD1F073",
                                    "username": "eleanore_interiorart"
                                },
                                "seen": null
                            },
                            "requested_by_viewer": false,
                            "username": "eleanore_interiorart"
                        }
                    },
                    {
                        "node": {
                            "followed_by_viewer": false,
                            "full_name": "Ruslana Kozlovska",
                            "id": "3949584675",
                            "is_private": false,
                            "is_verified": false,
                            "profile_pic_url": "https://scontent-frt3-2.cdninstagram.com/v/t51.2885-19/s150x150/109854827_293710258611638_5444851295667065961_n.jpg?_nc_ht=scontent-frt3-2.cdninstagram.com&_nc_ohc=Oupt9-e0jVsAX_R7uHQ&oh=58727199fd57fca06dd36ffe55f390ff&oe=5FD14AEC",
                            "reel": {
                                "expiring_at": 1604915178,
                                "has_pride_media": false,
                                "id": "3949584675",
                                "latest_reel_media": 1604769587,
                                "owner": {
                                    "__typename": "GraphUser",
                                    "id": "3949584675",
                                    "profile_pic_url": "https://scontent-frt3-2.cdninstagram.com/v/t51.2885-19/s150x150/109854827_293710258611638_5444851295667065961_n.jpg?_nc_ht=scontent-frt3-2.cdninstagram.com&_nc_ohc=Oupt9-e0jVsAX_R7uHQ&oh=58727199fd57fca06dd36ffe55f390ff&oe=5FD14AEC",
                                    "username": "kozlovskaya.ruslana"
                                },
                                "seen": null
                            },
                            "requested_by_viewer": false,
                            "username": "kozlovskaya.ruslana"
                        }
                    },
                    {
                        "node": {
                            "followed_by_viewer": false,
                            "full_name": "SHALIMOVA MARINA | \ud83c\udf19",
                            "id": "349289604",
                            "is_private": false,
                            "is_verified": false,
                            "profile_pic_url": "https://scontent-frt3-2.cdninstagram.com/v/t51.2885-19/s150x150/96115437_1268607853348043_2350242272290799616_n.jpg?_nc_ht=scontent-frt3-2.cdninstagram.com&_nc_ohc=XwoMkDN3vywAX9MGDU9&oh=de453aa26f63d85122a44b19b8375998&oe=5FD21E3B",
                            "reel": {
                                "expiring_at": 1604915178,
                                "has_pride_media": false,
                                "id": "349289604",
                                "latest_reel_media": 1604766068,
                                "owner": {
                                    "__typename": "GraphUser",
                                    "id": "349289604",
                                    "profile_pic_url": "https://scontent-frt3-2.cdninstagram.com/v/t51.2885-19/s150x150/96115437_1268607853348043_2350242272290799616_n.jpg?_nc_ht=scontent-frt3-2.cdninstagram.com&_nc_ohc=XwoMkDN3vywAX9MGDU9&oh=de453aa26f63d85122a44b19b8375998&oe=5FD21E3B",
                                    "username": "shal1mova"
                                },
                                "seen": null
                            },
                            "requested_by_viewer": false,
                            "username": "shal1mova"
                        }
                    },
                    {
                        "node": {
                            "followed_by_viewer": false,
                            "full_name": "",
                            "id": "864039577",
                            "is_private": true,
                            "is_verified": false,
                            "profile_pic_url": "https://scontent-frt3-2.cdninstagram.com/v/t51.2885-19/s150x150/14269077_306270189744624_544898223_a.jpg?_nc_ht=scontent-frt3-2.cdninstagram.com&_nc_ohc=ZCAJRD4QY-wAX_no43U&oh=8cb5856134cd2a20005356148cd8c225&oe=5FD04A2E",
                            "reel": {
                                "expiring_at": 1604915178,
                                "has_pride_media": false,
                                "id": "864039577",
                                "latest_reel_media": null,
                                "owner": {
                                    "__typename": "GraphUser",
                                    "id": "864039577",
                                    "profile_pic_url": "https://scontent-frt3-2.cdninstagram.com/v/t51.2885-19/s150x150/14269077_306270189744624_544898223_a.jpg?_nc_ht=scontent-frt3-2.cdninstagram.com&_nc_ohc=ZCAJRD4QY-wAX_no43U&oh=8cb5856134cd2a20005356148cd8c225&oe=5FD04A2E",
                                    "username": "im_tanyanchins"
                                },
                                "seen": null
                            },
                            "requested_by_viewer": false,
                            "username": "im_tanyanchins"
                        }
                    },
                    {
                        "node": {
                            "followed_by_viewer": false,
                            "full_name": "\u0411\u043e\u0440\u0438\u0441",
                            "id": "495664420",
                            "is_private": false,
                            "is_verified": false,
                            "profile_pic_url": "https://scontent-frt3-2.cdninstagram.com/v/t51.2885-19/s150x150/13150984_568582566649671_439953604_a.jpg?_nc_ht=scontent-frt3-2.cdninstagram.com&_nc_ohc=P1QQWsVCUF8AX_0TNhd&oh=bd3119c9732d56485fae6a19ce8d5d54&oe=5FCFF915",
                            "reel": {
                                "expiring_at": 1604915178,
                                "has_pride_media": false,
                                "id": "495664420",
                                "latest_reel_media": 0,
                                "owner": {
                                    "__typename": "GraphUser",
                                    "id": "495664420",
                                    "profile_pic_url": "https://scontent-frt3-2.cdninstagram.com/v/t51.2885-19/s150x150/13150984_568582566649671_439953604_a.jpg?_nc_ht=scontent-frt3-2.cdninstagram.com&_nc_ohc=P1QQWsVCUF8AX_0TNhd&oh=bd3119c9732d56485fae6a19ce8d5d54&oe=5FCFF915",
                                    "username": "borislogachev"
                                },
                                "seen": null
                            },
                            "requested_by_viewer": false,
                            "username": "borislogachev"
                        }
                    },
                    {
                        "node": {
                            "followed_by_viewer": false,
                            "full_name": "\u0410\u043d\u0430\u0441\u0442\u0430\u0441\u0438\u044f \u0410\u043b\u0435\u0445\u0438\u043d\u0430",
                            "id": "1442795005",
                            "is_private": true,
                            "is_verified": false,
                            "profile_pic_url": "https://scontent-frt3-2.cdninstagram.com/v/t51.2885-19/s150x150/66313388_538405290411565_2217032491510792192_n.jpg?_nc_ht=scontent-frt3-2.cdninstagram.com&_nc_ohc=_uxRjue-SUwAX9rOWOD&oh=5f90ecf2d5708e2d06a8b3b09d724b01&oe=5FD1366B",
                            "reel": {
                                "expiring_at": 1604915178,
                                "has_pride_media": false,
                                "id": "1442795005",
                                "latest_reel_media": null,
                                "owner": {
                                    "__typename": "GraphUser",
                                    "id": "1442795005",
                                    "profile_pic_url": "https://scontent-frt3-2.cdninstagram.com/v/t51.2885-19/s150x150/66313388_538405290411565_2217032491510792192_n.jpg?_nc_ht=scontent-frt3-2.cdninstagram.com&_nc_ohc=_uxRjue-SUwAX9rOWOD&oh=5f90ecf2d5708e2d06a8b3b09d724b01&oe=5FD1366B",
                                    "username": "alekhinastya"
                                },
                                "seen": null
                            },
                            "requested_by_viewer": false,
                            "username": "alekhinastya"
                        }
                    },
                    {
                        "node": {
                            "followed_by_viewer": false,
                            "full_name": "\u041d\u0430\u0434\u0435\u0436\u0434\u0430\ud83e\udd17",
                            "id": "2157588377",
                            "is_private": false,
                            "is_verified": false,
                            "profile_pic_url": "https://scontent-frt3-2.cdninstagram.com/v/t51.2885-19/s150x150/71269858_2317923618537389_7020009640268136448_n.jpg?_nc_ht=scontent-frt3-2.cdninstagram.com&_nc_ohc=mdl3wvL27ZgAX8TVb2i&oh=341fcc333fea3bb278b83a123d263511&oe=5FD1A1F9",
                            "reel": {
                                "expiring_at": 1604915178,
                                "has_pride_media": false,
                                "id": "2157588377",
                                "latest_reel_media": 1604825815,
                                "owner": {
                                    "__typename": "GraphUser",
                                    "id": "2157588377",
                                    "profile_pic_url": "https://scontent-frt3-2.cdninstagram.com/v/t51.2885-19/s150x150/71269858_2317923618537389_7020009640268136448_n.jpg?_nc_ht=scontent-frt3-2.cdninstagram.com&_nc_ohc=mdl3wvL27ZgAX8TVb2i&oh=341fcc333fea3bb278b83a123d263511&oe=5FD1A1F9",
                                    "username": "yakovleva05061991"
                                },
                                "seen": null
                            },
                            "requested_by_viewer": false,
                            "username": "yakovleva05061991"
                        }
                    },
                    {
                        "node": {
                            "followed_by_viewer": false,
                            "full_name": "Elena Besedina",
                            "id": "2316761297",
                            "is_private": false,
                            "is_verified": false,
                            "profile_pic_url": "https://scontent-frt3-2.cdninstagram.com/v/t51.2885-19/s150x150/71513830_388958108660780_2163357713982029824_n.jpg?_nc_ht=scontent-frt3-2.cdninstagram.com&_nc_ohc=5nEMBjmLMT8AX_PY1xw&oh=35a2828e7f00d079090acbc2fd746712&oe=5FD20082",
                            "reel": {
                                "expiring_at": 1604915178,
                                "has_pride_media": false,
                                "id": "2316761297",
                                "latest_reel_media": 0,
                                "owner": {
                                    "__typename": "GraphUser",
                                    "id": "2316761297",
                                    "profile_pic_url": "https://scontent-frt3-2.cdninstagram.com/v/t51.2885-19/s150x150/71513830_388958108660780_2163357713982029824_n.jpg?_nc_ht=scontent-frt3-2.cdninstagram.com&_nc_ohc=5nEMBjmLMT8AX_PY1xw&oh=35a2828e7f00d079090acbc2fd746712&oe=5FD20082",
                                    "username": "elena.besedina"
                                },
                                "seen": null
                            },
                            "requested_by_viewer": false,
                            "username": "elena.besedina"
                        }
                    },
                    {
                        "node": {
                            "followed_by_viewer": false,
                            "full_name": "\u0413\u0440\u0438\u0433\u043e\u0440\u0438\u0439 \u0421\u0430\u0444\u043e\u043d\u043e\u0432",
                            "id": "3056881918",
                            "is_private": false,
                            "is_verified": false,
                            "profile_pic_url": "https://scontent-frt3-2.cdninstagram.com/v/t51.2885-19/s150x150/97111087_648925055672327_7621318685344399360_n.jpg?_nc_ht=scontent-frt3-2.cdninstagram.com&_nc_ohc=630EkSsA79AAX8Evuv-&oh=dce94ab5b12dc74bf138bbc196e41e35&oe=5FD0F32E",
                            "reel": {
                                "expiring_at": 1604915178,
                                "has_pride_media": false,
                                "id": "3056881918",
                                "latest_reel_media": 0,
                                "owner": {
                                    "__typename": "GraphUser",
                                    "id": "3056881918",
                                    "profile_pic_url": "https://scontent-frt3-2.cdninstagram.com/v/t51.2885-19/s150x150/97111087_648925055672327_7621318685344399360_n.jpg?_nc_ht=scontent-frt3-2.cdninstagram.com&_nc_ohc=630EkSsA79AAX8Evuv-&oh=dce94ab5b12dc74bf138bbc196e41e35&oe=5FD0F32E",
                                    "username": "jam_good17"
                                },
                                "seen": null
                            },
                            "requested_by_viewer": false,
                            "username": "jam_good17"
                        }
                    },
                    {
                        "node": {
                            "followed_by_viewer": false,
                            "full_name": "\u0425\u043e\u0445\u0440\u044f\u043a\u043e\u0432\u0430 \u0410\u043d\u043d\u0430",
                            "id": "1410664301",
                            "is_private": false,
                            "is_verified": false,
                            "profile_pic_url": "https://scontent-frt3-2.cdninstagram.com/v/t51.2885-19/s150x150/28427998_2022978191302016_3927871690977050624_n.jpg?_nc_ht=scontent-frt3-2.cdninstagram.com&_nc_ohc=F40r0jEqpQYAX8Fa2Fi&oh=847fd809c936fc736297510a2ffc6dc4&oe=5FD05FC5",
                            "reel": {
                                "expiring_at": 1604915178,
                                "has_pride_media": false,
                                "id": "1410664301",
                                "latest_reel_media": 1604775562,
                                "owner": {
                                    "__typename": "GraphUser",
                                    "id": "1410664301",
                                    "profile_pic_url": "https://scontent-frt3-2.cdninstagram.com/v/t51.2885-19/s150x150/28427998_2022978191302016_3927871690977050624_n.jpg?_nc_ht=scontent-frt3-2.cdninstagram.com&_nc_ohc=F40r0jEqpQYAX8Fa2Fi&oh=847fd809c936fc736297510a2ffc6dc4&oe=5FD05FC5",
                                    "username": "anya_khokh"
                                },
                                "seen": null
                            },
                            "requested_by_viewer": false,
                            "username": "anya_khokh"
                        }
                    },
                    {
                        "node": {
                            "followed_by_viewer": false,
                            "full_name": "\u041f\u041e\u0414\u0410\u0420\u041a\u0418 \u0418\u0417 \u0414\u0415\u0420\u0415\u0412\u0410 \u0421 \u041b\u042e\u0411\u041e\u0412\u042c\u042e\u2764\ufe0f",
                            "id": "10639492763",
                            "is_private": false,
                            "is_verified": false,
                            "profile_pic_url": "https://scontent-frt3-2.cdninstagram.com/v/t51.2885-19/s150x150/117953998_368818180782972_7613039157498107675_n.jpg?_nc_ht=scontent-frt3-2.cdninstagram.com&_nc_ohc=W36HRBbvnE8AX_-8sRO&oh=81e7edc2badce3daee3b64f82a21b95b&oe=5FD2588F",
                            "reel": {
                                "expiring_at": 1604915178,
                                "has_pride_media": false,
                                "id": "10639492763",
                                "latest_reel_media": 0,
                                "owner": {
                                    "__typename": "GraphUser",
                                    "id": "10639492763",
                                    "profile_pic_url": "https://scontent-frt3-2.cdninstagram.com/v/t51.2885-19/s150x150/117953998_368818180782972_7613039157498107675_n.jpg?_nc_ht=scontent-frt3-2.cdninstagram.com&_nc_ohc=W36HRBbvnE8AX_-8sRO&oh=81e7edc2badce3daee3b64f82a21b95b&oe=5FD2588F",
                                    "username": "workshop.vsv"
                                },
                                "seen": null
                            },
                            "requested_by_viewer": false,
                            "username": "workshop.vsv"
                        }
                    },
                    {
                        "node": {
                            "followed_by_viewer": false,
                            "full_name": "\u2022\u041f\u041b\u0410\u041d\u0418\u0420\u041e\u0412\u041a\u0418\u2022\u0418\u041d\u0422\u0415\u0420\u042c\u0415\u0420\u042b\u2022\u0418\u041a\u0415\u0410",
                            "id": "5661857583",
                            "is_private": false,
                            "is_verified": false,
                            "profile_pic_url": "https://scontent-frt3-2.cdninstagram.com/v/t51.2885-19/s150x150/106103779_263121024788140_2201972564751378807_n.jpg?_nc_ht=scontent-frt3-2.cdninstagram.com&_nc_ohc=oI9Nn8F0w-UAX9_fnxZ&oh=ea5a82a229dd013b77de4dc4fa38db3d&oe=5FD33BFC",
                            "reel": {
                                "expiring_at": 1604915178,
                                "has_pride_media": false,
                                "id": "5661857583",
                                "latest_reel_media": 0,
                                "owner": {
                                    "__typename": "GraphUser",
                                    "id": "5661857583",
                                    "profile_pic_url": "https://scontent-frt3-2.cdninstagram.com/v/t51.2885-19/s150x150/106103779_263121024788140_2201972564751378807_n.jpg?_nc_ht=scontent-frt3-2.cdninstagram.com&_nc_ohc=oI9Nn8F0w-UAX9_fnxZ&oh=ea5a82a229dd013b77de4dc4fa38db3d&oe=5FD33BFC",
                                    "username": "chermeneva_design"
                                },
                                "seen": null
                            },
                            "requested_by_viewer": false,
                            "username": "chermeneva_design"
                        }
                    },
                    {
                        "node": {
                            "followed_by_viewer": false,
                            "full_name": "\u0417\u0438\u043b\u044f",
                            "id": "728493265",
                            "is_private": true,
                            "is_verified": false,
                            "profile_pic_url": "https://scontent-frt3-2.cdninstagram.com/v/t51.2885-19/s150x150/84636243_192699781798781_8451611373481230336_n.jpg?_nc_ht=scontent-frt3-2.cdninstagram.com&_nc_ohc=lnSLaVarYFIAX8Axv0c&oh=af2d62a421a8c06e2271f5703c218554&oe=5FD2B157",
                            "reel": {
                                "expiring_at": 1604915178,
                                "has_pride_media": false,
                                "id": "728493265",
                                "latest_reel_media": null,
                                "owner": {
                                    "__typename": "GraphUser",
                                    "id": "728493265",
                                    "profile_pic_url": "https://scontent-frt3-2.cdninstagram.com/v/t51.2885-19/s150x150/84636243_192699781798781_8451611373481230336_n.jpg?_nc_ht=scontent-frt3-2.cdninstagram.com&_nc_ohc=lnSLaVarYFIAX8Axv0c&oh=af2d62a421a8c06e2271f5703c218554&oe=5FD2B157",
                                    "username": "zilailyk"
                                },
                                "seen": null
                            },
                            "requested_by_viewer": false,
                            "username": "zilailyk"
                        }
                    },
                    {
                        "node": {
                            "followed_by_viewer": false,
                            "full_name": "\u0415\u0433\u043e\u0440",
                            "id": "3968396090",
                            "is_private": false,
                            "is_verified": false,
                            "profile_pic_url": "https://scontent-frt3-2.cdninstagram.com/v/t51.2885-19/s150x150/119230434_980317049149517_2935064940413842471_n.jpg?_nc_ht=scontent-frt3-2.cdninstagram.com&_nc_ohc=F_a3KlerpM8AX9fpRRd&oh=c6d6ca9121870a3b19f24943ddd70f32&oe=5FD11072",
                            "reel": {
                                "expiring_at": 1604915178,
                                "has_pride_media": false,
                                "id": "3968396090",
                                "latest_reel_media": 0,
                                "owner": {
                                    "__typename": "GraphUser",
                                    "id": "3968396090",
                                    "profile_pic_url": "https://scontent-frt3-2.cdninstagram.com/v/t51.2885-19/s150x150/119230434_980317049149517_2935064940413842471_n.jpg?_nc_ht=scontent-frt3-2.cdninstagram.com&_nc_ohc=F_a3KlerpM8AX9fpRRd&oh=c6d6ca9121870a3b19f24943ddd70f32&oe=5FD11072",
                                    "username": "egornikishanov"
                                },
                                "seen": null
                            },
                            "requested_by_viewer": false,
                            "username": "egornikishanov"
                        }
                    },
                    {
                        "node": {
                            "followed_by_viewer": false,
                            "full_name": "\ud83d\udc67\u041a\u0420\u041e\u0412\u0410\u0422\u041a\u0418-\u0414\u041e\u041c\u0418\u041a\u0418 \u0414\u041b\u042f \u0414\u0415\u0422\u0415\u0419\ud83d\udc68",
                            "id": "37476422730",
                            "is_private": false,
                            "is_verified": false,
                            "profile_pic_url": "https://scontent-frt3-2.cdninstagram.com/v/t51.2885-19/s150x150/104211552_2639868663001361_431525155875351895_n.jpg?_nc_ht=scontent-frt3-2.cdninstagram.com&_nc_ohc=R0UVjoDaKlUAX_AAN7w&oh=cd8d65cd42fd015e5184851ff58c706d&oe=5FD2C473",
                            "reel": {
                                "expiring_at": 1604915178,
                                "has_pride_media": false,
                                "id": "37476422730",
                                "latest_reel_media": 0,
                                "owner": {
                                    "__typename": "GraphUser",
                                    "id": "37476422730",
                                    "profile_pic_url": "https://scontent-frt3-2.cdninstagram.com/v/t51.2885-19/s150x150/104211552_2639868663001361_431525155875351895_n.jpg?_nc_ht=scontent-frt3-2.cdninstagram.com&_nc_ohc=R0UVjoDaKlUAX_AAN7w&oh=cd8d65cd42fd015e5184851ff58c706d&oe=5FD2C473",
                                    "username": "woodbunnybed"
                                },
                                "seen": null
                            },
                            "requested_by_viewer": false,
                            "username": "woodbunnybed"
                        }
                    },
                    {
                        "node": {
                            "followed_by_viewer": false,
                            "full_name": "",
                            "id": "3300251218",
                            "is_private": false,
                            "is_verified": false,
                            "profile_pic_url": "https://scontent-frt3-2.cdninstagram.com/v/t51.2885-19/s150x150/117724417_1168321560190626_2564843090353034840_n.jpg?_nc_ht=scontent-frt3-2.cdninstagram.com&_nc_ohc=u5Bkznt7mpsAX_KEXjy&oh=e9195bd43983a6e00b5ac4e8037d8595&oe=5FD2BDD7",
                            "reel": {
                                "expiring_at": 1604915178,
                                "has_pride_media": false,
                                "id": "3300251218",
                                "latest_reel_media": 0,
                                "owner": {
                                    "__typename": "GraphUser",
                                    "id": "3300251218",
                                    "profile_pic_url": "https://scontent-frt3-2.cdninstagram.com/v/t51.2885-19/s150x150/117724417_1168321560190626_2564843090353034840_n.jpg?_nc_ht=scontent-frt3-2.cdninstagram.com&_nc_ohc=u5Bkznt7mpsAX_KEXjy&oh=e9195bd43983a6e00b5ac4e8037d8595&oe=5FD2BDD7",
                                    "username": "yakhin_konstantin"
                                },
                                "seen": null
                            },
                            "requested_by_viewer": false,
                            "username": "yakhin_konstantin"
                        }
                    },
                    {
                        "node": {
                            "followed_by_viewer": false,
                            "full_name": "KRAFT",
                            "id": "6458188750",
                            "is_private": false,
                            "is_verified": false,
                            "profile_pic_url": "https://scontent-frt3-2.cdninstagram.com/v/t51.2885-19/s150x150/26868426_182693235830600_2328176856332763136_n.jpg?_nc_ht=scontent-frt3-2.cdninstagram.com&_nc_ohc=YN09y75rjlQAX-EgQ4M&oh=962b3dc0b394d88058b967413e0a0c2b&oe=5FD04649",
                            "reel": {
                                "expiring_at": 1604915178,
                                "has_pride_media": false,
                                "id": "6458188750",
                                "latest_reel_media": 0,
                                "owner": {
                                    "__typename": "GraphUser",
                                    "id": "6458188750",
                                    "profile_pic_url": "https://scontent-frt3-2.cdninstagram.com/v/t51.2885-19/s150x150/26868426_182693235830600_2328176856332763136_n.jpg?_nc_ht=scontent-frt3-2.cdninstagram.com&_nc_ohc=YN09y75rjlQAX-EgQ4M&oh=962b3dc0b394d88058b967413e0a0c2b&oe=5FD04649",
                                    "username": "kraft_masterskaya"
                                },
                                "seen": null
                            },
                            "requested_by_viewer": false,
                            "username": "kraft_masterskaya"
                        }
                    },
                    {
                        "node": {
                            "followed_by_viewer": false,
                            "full_name": "\ud835\udcd0\ud835\udcf7\ud835\udcf7\ud835\udcea \ud835\udcec\ud835\udcf1\ud835\udcee\ud835\udceb\ud835\udcea\ud835\udcf4\ud835\udcf8\ud835\udce5\ud835\udcea",
                            "id": "611261621",
                            "is_private": false,
                            "is_verified": false,
                            "profile_pic_url": "https://scontent-frt3-2.cdninstagram.com/v/t51.2885-19/s150x150/110266580_3189851494410169_1342134720381715644_n.jpg?_nc_ht=scontent-frt3-2.cdninstagram.com&_nc_ohc=2QKfCKCLOVwAX-4FHTj&oh=c9fc56f846b64eed73909008af3317f4&oe=5FD16D7A",
                            "reel": {
                                "expiring_at": 1604915178,
                                "has_pride_media": false,
                                "id": "611261621",
                                "latest_reel_media": 1604788057,
                                "owner": {
                                    "__typename": "GraphUser",
                                    "id": "611261621",
                                    "profile_pic_url": "https://scontent-frt3-2.cdninstagram.com/v/t51.2885-19/s150x150/110266580_3189851494410169_1342134720381715644_n.jpg?_nc_ht=scontent-frt3-2.cdninstagram.com&_nc_ohc=2QKfCKCLOVwAX-4FHTj&oh=c9fc56f846b64eed73909008af3317f4&oe=5FD16D7A",
                                    "username": "anitachebakova"
                                },
                                "seen": null
                            },
                            "requested_by_viewer": false,
                            "username": "anitachebakova"
                        }
                    },
                    {
                        "node": {
                            "followed_by_viewer": false,
                            "full_name": "\ud83d\udc0c",
                            "id": "312869447",
                            "is_private": false,
                            "is_verified": false,
                            "profile_pic_url": "https://scontent-frt3-2.cdninstagram.com/v/t51.2885-19/s150x150/35948698_1888750717813275_4327172137606447104_n.jpg?_nc_ht=scontent-frt3-2.cdninstagram.com&_nc_ohc=nCzrWix8Q1AAX_BFZI9&oh=96aa88e8e6883150c859d9b6d0adaaee&oe=5FD0E86E",
                            "reel": {
                                "expiring_at": 1604915178,
                                "has_pride_media": false,
                                "id": "312869447",
                                "latest_reel_media": 0,
                                "owner": {
                                    "__typename": "GraphUser",
                                    "id": "312869447",
                                    "profile_pic_url": "https://scontent-frt3-2.cdninstagram.com/v/t51.2885-19/s150x150/35948698_1888750717813275_4327172137606447104_n.jpg?_nc_ht=scontent-frt3-2.cdninstagram.com&_nc_ohc=nCzrWix8Q1AAX_BFZI9&oh=96aa88e8e6883150c859d9b6d0adaaee&oe=5FD0E86E",
                                    "username": "anyta_116"
                                },
                                "seen": null
                            },
                            "requested_by_viewer": false,
                            "username": "anyta_116"
                        }
                    },
                    {
                        "node": {
                            "followed_by_viewer": false,
                            "full_name": "",
                            "id": "20918595",
                            "is_private": false,
                            "is_verified": false,
                            "profile_pic_url": "https://scontent-frt3-2.cdninstagram.com/v/t51.2885-19/s150x150/87433888_528780337771787_3242016433722359808_n.jpg?_nc_ht=scontent-frt3-2.cdninstagram.com&_nc_ohc=Y7n_hEo5EukAX8DlZBS&oh=c187a25935e792bbd03a3b77ed845ff0&oe=5FCFB2F8",
                            "reel": {
                                "expiring_at": 1604915178,
                                "has_pride_media": false,
                                "id": "20918595",
                                "latest_reel_media": 0,
                                "owner": {
                                    "__typename": "GraphUser",
                                    "id": "20918595",
                                    "profile_pic_url": "https://scontent-frt3-2.cdninstagram.com/v/t51.2885-19/s150x150/87433888_528780337771787_3242016433722359808_n.jpg?_nc_ht=scontent-frt3-2.cdninstagram.com&_nc_ohc=Y7n_hEo5EukAX8DlZBS&oh=c187a25935e792bbd03a3b77ed845ff0&oe=5FCFB2F8",
                                    "username": "_balashovava_"
                                },
                                "seen": null
                            },
                            "requested_by_viewer": false,
                            "username": "_balashovava_"
                        }
                    },
                    {
                        "node": {
                            "followed_by_viewer": false,
                            "full_name": "",
                            "id": "3124260712",
                            "is_private": true,
                            "is_verified": false,
                            "profile_pic_url": "https://scontent-frt3-2.cdninstagram.com/v/t51.2885-19/s150x150/106623077_269589944368916_851535703832683049_n.jpg?_nc_ht=scontent-frt3-2.cdninstagram.com&_nc_ohc=2sOnu-z0MckAX--DDNm&oh=8d0e77b29116db4fd65e53a79e3c5b94&oe=5FD1E344",
                            "reel": {
                                "expiring_at": 1604915178,
                                "has_pride_media": false,
                                "id": "3124260712",
                                "latest_reel_media": null,
                                "owner": {
                                    "__typename": "GraphUser",
                                    "id": "3124260712",
                                    "profile_pic_url": "https://scontent-frt3-2.cdninstagram.com/v/t51.2885-19/s150x150/106623077_269589944368916_851535703832683049_n.jpg?_nc_ht=scontent-frt3-2.cdninstagram.com&_nc_ohc=2sOnu-z0MckAX--DDNm&oh=8d0e77b29116db4fd65e53a79e3c5b94&oe=5FD1E344",
                                    "username": "irinkaxacko1986"
                                },
                                "seen": null
                            },
                            "requested_by_viewer": false,
                            "username": "irinkaxacko1986"
                        }
                    },
                    {
                        "node": {
                            "followed_by_viewer": false,
                            "full_name": "\u0421\u0435\u0440\u0433\u0435\u0439 \u041a\u0430\u0437\u0430\u043a\u043e\u0432",
                            "id": "3198505865",
                            "is_private": true,
                            "is_verified": false,
                            "profile_pic_url": "https://scontent-frt3-2.cdninstagram.com/v/t51.2885-19/s150x150/42851024_280777249437715_4425050877459431424_n.jpg?_nc_ht=scontent-frt3-2.cdninstagram.com&_nc_ohc=ZwlGyhczYZwAX8qyGtc&oh=d60fc2dfa35faf816fc7c4603041b361&oe=5FD188AA",
                            "reel": {
                                "expiring_at": 1604915178,
                                "has_pride_media": false,
                                "id": "3198505865",
                                "latest_reel_media": null,
                                "owner": {
                                    "__typename": "GraphUser",
                                    "id": "3198505865",
                                    "profile_pic_url": "https://scontent-frt3-2.cdninstagram.com/v/t51.2885-19/s150x150/42851024_280777249437715_4425050877459431424_n.jpg?_nc_ht=scontent-frt3-2.cdninstagram.com&_nc_ohc=ZwlGyhczYZwAX8qyGtc&oh=d60fc2dfa35faf816fc7c4603041b361&oe=5FD188AA",
                                    "username": "kazakovlsergey"
                                },
                                "seen": null
                            },
                            "requested_by_viewer": false,
                            "username": "kazakovlsergey"
                        }
                    },
                    {
                        "node": {
                            "followed_by_viewer": false,
                            "full_name": "\u041e\u043b\u044c\u0433\u0430",
                            "id": "4514659641",
                            "is_private": false,
                            "is_verified": false,
                            "profile_pic_url": "https://scontent-frt3-2.cdninstagram.com/v/t51.2885-19/s150x150/81736502_1349348611932655_9166703113069920256_n.jpg?_nc_ht=scontent-frt3-2.cdninstagram.com&_nc_ohc=UJtfjmZ_htIAX_xsdn3&oh=2d394db931569cf39e8a8680c2a1759b&oe=5FD0EBF6",
                            "reel": {
                                "expiring_at": 1604915178,
                                "has_pride_media": false,
                                "id": "4514659641",
                                "latest_reel_media": 0,
                                "owner": {
                                    "__typename": "GraphUser",
                                    "id": "4514659641",
                                    "profile_pic_url": "https://scontent-frt3-2.cdninstagram.com/v/t51.2885-19/s150x150/81736502_1349348611932655_9166703113069920256_n.jpg?_nc_ht=scontent-frt3-2.cdninstagram.com&_nc_ohc=UJtfjmZ_htIAX_xsdn3&oh=2d394db931569cf39e8a8680c2a1759b&oe=5FD0EBF6",
                                    "username": "ole4ka_isynbaeva"
                                },
                                "seen": null
                            },
                            "requested_by_viewer": false,
                            "username": "ole4ka_isynbaeva"
                        }
                    },
                    {
                        "node": {
                            "followed_by_viewer": false,
                            "full_name": "",
                            "id": "4639275420",
                            "is_private": true,
                            "is_verified": false,
                            "profile_pic_url": "https://scontent-frt3-2.cdninstagram.com/v/t51.2885-19/s150x150/50100470_1954453244863428_3611028036540956672_n.jpg?_nc_ht=scontent-frt3-2.cdninstagram.com&_nc_ohc=kPMlCxDIXhAAX9-_FZQ&oh=199b3704a272e8dd4f092ef7e63e68fb&oe=5FD1A249",
                            "reel": {
                                "expiring_at": 1604915178,
                                "has_pride_media": false,
                                "id": "4639275420",
                                "latest_reel_media": null,
                                "owner": {
                                    "__typename": "GraphUser",
                                    "id": "4639275420",
                                    "profile_pic_url": "https://scontent-frt3-2.cdninstagram.com/v/t51.2885-19/s150x150/50100470_1954453244863428_3611028036540956672_n.jpg?_nc_ht=scontent-frt3-2.cdninstagram.com&_nc_ohc=kPMlCxDIXhAAX9-_FZQ&oh=199b3704a272e8dd4f092ef7e63e68fb&oe=5FD1A249",
                                    "username": "mrs.alarmist"
                                },
                                "seen": null
                            },
                            "requested_by_viewer": false,
                            "username": "mrs.alarmist"
                        }
                    },
                    {
                        "node": {
                            "followed_by_viewer": false,
                            "full_name": "Natawell5",
                            "id": "5880615266",
                            "is_private": true,
                            "is_verified": false,
                            "profile_pic_url": "https://scontent-frt3-2.cdninstagram.com/v/t51.2885-19/s150x150/42136178_2144064055920194_1525143479515086848_n.jpg?_nc_ht=scontent-frt3-2.cdninstagram.com&_nc_ohc=OZ_zTFhsD5EAX-2Ck0x&oh=cecd915ec28d657b2922d3d412a91224&oe=5FD16AAB",
                            "reel": {
                                "expiring_at": 1604915178,
                                "has_pride_media": false,
                                "id": "5880615266",
                                "latest_reel_media": null,
                                "owner": {
                                    "__typename": "GraphUser",
                                    "id": "5880615266",
                                    "profile_pic_url": "https://scontent-frt3-2.cdninstagram.com/v/t51.2885-19/s150x150/42136178_2144064055920194_1525143479515086848_n.jpg?_nc_ht=scontent-frt3-2.cdninstagram.com&_nc_ohc=OZ_zTFhsD5EAX-2Ck0x&oh=cecd915ec28d657b2922d3d412a91224&oe=5FD16AAB",
                                    "username": "natawell5"
                                },
                                "seen": null
                            },
                            "requested_by_viewer": false,
                            "username": "natawell5"
                        }
                    },
                    {
                        "node": {
                            "followed_by_viewer": false,
                            "full_name": "\u041c\u0435\u043b\u044c\u043d\u0438\u043a\u043e\u0432 \u0412\u0430\u043b\u0435\u043d\u0442\u0438\u043d",
                            "id": "2239116024",
                            "is_private": false,
                            "is_verified": false,
                            "profile_pic_url": "https://scontent-frt3-2.cdninstagram.com/v/t51.2885-19/s150x150/47694422_779203452437154_5065257710463746048_n.jpg?_nc_ht=scontent-frt3-2.cdninstagram.com&_nc_ohc=0epvYxUpyvIAX_WpYHM&oh=064a9638cd297a8f6fd55bdb49a7ffdf&oe=5FD13696",
                            "reel": {
                                "expiring_at": 1604915178,
                                "has_pride_media": false,
                                "id": "2239116024",
                                "latest_reel_media": 0,
                                "owner": {
                                    "__typename": "GraphUser",
                                    "id": "2239116024",
                                    "profile_pic_url": "https://scontent-frt3-2.cdninstagram.com/v/t51.2885-19/s150x150/47694422_779203452437154_5065257710463746048_n.jpg?_nc_ht=scontent-frt3-2.cdninstagram.com&_nc_ohc=0epvYxUpyvIAX_WpYHM&oh=064a9638cd297a8f6fd55bdb49a7ffdf&oe=5FD13696",
                                    "username": "melnikov_valentin_013"
                                },
                                "seen": null
                            },
                            "requested_by_viewer": false,
                            "username": "melnikov_valentin_013"
                        }
                    },
                    {
                        "node": {
                            "followed_by_viewer": false,
                            "full_name": "",
                            "id": "1636430034",
                            "is_private": false,
                            "is_verified": false,
                            "profile_pic_url": "https://scontent-frt3-2.cdninstagram.com/v/t51.2885-19/s150x150/64329466_608589976292539_8306717864316895232_n.jpg?_nc_ht=scontent-frt3-2.cdninstagram.com&_nc_ohc=MDI-pLewQAoAX9PNQcJ&oh=4d0cfafae8f36e8df37368bedbddced8&oe=5FD27385",
                            "reel": {
                                "expiring_at": 1604915178,
                                "has_pride_media": false,
                                "id": "1636430034",
                                "latest_reel_media": 0,
                                "owner": {
                                    "__typename": "GraphUser",
                                    "id": "1636430034",
                                    "profile_pic_url": "https://scontent-frt3-2.cdninstagram.com/v/t51.2885-19/s150x150/64329466_608589976292539_8306717864316895232_n.jpg?_nc_ht=scontent-frt3-2.cdninstagram.com&_nc_ohc=MDI-pLewQAoAX9PNQcJ&oh=4d0cfafae8f36e8df37368bedbddced8&oe=5FD27385",
                                    "username": "muha_pokaluha"
                                },
                                "seen": null
                            },
                            "requested_by_viewer": false,
                            "username": "muha_pokaluha"
                        }
                    },
                    {
                        "node": {
                            "followed_by_viewer": false,
                            "full_name": "Vladislav Badmaev",
                            "id": "1581427904",
                            "is_private": false,
                            "is_verified": false,
                            "profile_pic_url": "https://scontent-frt3-2.cdninstagram.com/v/t51.2885-19/s150x150/71699399_569816030507472_1651917457960468480_n.jpg?_nc_ht=scontent-frt3-2.cdninstagram.com&_nc_ohc=C0giSIUfk-oAX_GRKj_&oh=14c56a07a41bd419c92d41f157b3aa2c&oe=5FD26022",
                            "reel": {
                                "expiring_at": 1604915178,
                                "has_pride_media": false,
                                "id": "1581427904",
                                "latest_reel_media": 0,
                                "owner": {
                                    "__typename": "GraphUser",
                                    "id": "1581427904",
                                    "profile_pic_url": "https://scontent-frt3-2.cdninstagram.com/v/t51.2885-19/s150x150/71699399_569816030507472_1651917457960468480_n.jpg?_nc_ht=scontent-frt3-2.cdninstagram.com&_nc_ohc=C0giSIUfk-oAX_GRKj_&oh=14c56a07a41bd419c92d41f157b3aa2c&oe=5FD26022",
                                    "username": "badmaevladislav"
                                },
                                "seen": null
                            },
                            "requested_by_viewer": false,
                            "username": "badmaevladislav"
                        }
                    }
                ],
                "page_info": {
                    "end_cursor": "QVFDWDRoWUlnSVBtLTN6UlVpNjlrUGRiQWZ5aGVSUXZkaHREeFFxWUs1clNpQXRWSjMyd3BNSzRrZVFMc2VyUS1zSHFFeGJJdVBycFhWVjAxS3ZBZEhYSA==",
                    "has_next_page": true
                }
            }
        }
    },
    "status": "ok"
}